senweaver_oauth/__init__.py
senweaver_oauth/builder.py
senweaver_oauth/config.py
senweaver_oauth/request.py
senweaver_oauth/cache/__init__.py
senweaver_oauth/cache/base.py
senweaver_oauth/cache/default.py
senweaver_oauth/cache/memory.py
senweaver_oauth/cache/redis.py
senweaver_oauth/enums/__init__.py
senweaver_oauth/enums/auth_gender.py
senweaver_oauth/enums/auth_scope.py
senweaver_oauth/enums/auth_source.py
senweaver_oauth/enums/response_status.py
senweaver_oauth/http/__init__.py
senweaver_oauth/http/http_client.py
senweaver_oauth/http/http_config.py
senweaver_oauth/http/requests_http_client.py
senweaver_oauth/model/__init__.py
senweaver_oauth/model/auth_callback.py
senweaver_oauth/model/auth_response.py
senweaver_oauth/model/auth_token.py
senweaver_oauth/model/auth_user.py
senweaver_oauth/source/__init__.py
senweaver_oauth/source/alipay.py
senweaver_oauth/source/aliyun.py
senweaver_oauth/source/amazon.py
senweaver_oauth/source/baidu.py
senweaver_oauth/source/base.py
senweaver_oauth/source/coding.py
senweaver_oauth/source/dingtalk.py
senweaver_oauth/source/douyin.py
senweaver_oauth/source/eleme.py
senweaver_oauth/source/facebook.py
senweaver_oauth/source/feishu.py
senweaver_oauth/source/gitee.py
senweaver_oauth/source/github.py
senweaver_oauth/source/gitlab.py
senweaver_oauth/source/google.py
senweaver_oauth/source/huawei.py
senweaver_oauth/source/jd.py
senweaver_oauth/source/kujiale.py
senweaver_oauth/source/line.py
senweaver_oauth/source/linkedin.py
senweaver_oauth/source/meituan.py
senweaver_oauth/source/microsoft.py
senweaver_oauth/source/oschina.py
senweaver_oauth/source/pinterest.py
senweaver_oauth/source/qq.py
senweaver_oauth/source/renren.py
senweaver_oauth/source/slack.py
senweaver_oauth/source/stack_overflow.py
senweaver_oauth/source/taobao.py
senweaver_oauth/source/teambition.py
senweaver_oauth/source/tencent_cloud.py
senweaver_oauth/source/toutiao.py
senweaver_oauth/source/twitter.py
senweaver_oauth/source/wechat.py
senweaver_oauth-0.1.3.dist-info/licenses/LICENSE
senweaver_oauth-0.1.3.dist-info/METADATA
senweaver_oauth-0.1.3.dist-info/WHEEL
senweaver_oauth-0.1.3.dist-info/top_level.txt
senweaver_oauth-0.1.3.dist-info/RECORD
