Metadata-Version: 2.4
Name: senweaver-oauth
Version: 0.1.3
Summary: 强大、灵活且易用的OAuth授权集成组件
Home-page: https://github.com/senweaver/senweaver-oauth
Author: senweaver
Project-URL: Bug Reports, https://github.com/senweaver/senweaver-oauth/issues
Project-URL: Source, https://github.com/senweaver/senweaver-oauth
Keywords: oauth,wechat,weixin,微信,senweaver
Classifier: Development Status :: 4 - Beta
Classifier: Intended Audience :: Developers
Classifier: License :: OSI Approved :: MIT License
Classifier: Programming Language :: Python :: 3
Classifier: Programming Language :: Python :: 3.8
Classifier: Programming Language :: Python :: 3.9
Classifier: Programming Language :: Python :: 3.10
Requires-Python: >=3.8
License-File: LICENSE
Requires-Dist: requests>=2.28.0
Requires-Dist: cryptography>=41.0.0
Requires-Dist: cachetools>=5.0.0
Requires-Dist: redis>=4.0.0
Dynamic: author
Dynamic: classifier
Dynamic: description
Dynamic: description-content-type
Dynamic: home-page
Dynamic: keywords
Dynamic: license-file
Dynamic: project-url
Dynamic: requires-dist
Dynamic: requires-python
Dynamic: summary
